figcon/__init__.py
figcon/core.py
figcon/version.py
figcon-0.0.0.dist-info/LICENSE
figcon-0.0.0.dist-info/METADATA
figcon-0.0.0.dist-info/WHEEL
figcon-0.0.0.dist-info/top_level.txt
figcon-0.0.0.dist-info/RECORD
