Metadata-Version: 2.1
Name: figcon
Version: 0.0.0
Summary: A simple way to configure python libraries
Home-page: https://bitbucket.org/smrd/figcon
Author: Derrick Chambers
Author-email: djachambeador@gmail.com
License: BSD
Keywords: figcon
Platform: UNKNOWN
Classifier: Development Status :: 2 - Pre-Alpha
Classifier: Intended Audience :: Developers
Classifier: License :: OSI Approved :: BSD License
Classifier: Programming Language :: Python :: 3.6
